{
  "class_name": "Desperado",
  "class_id": 5019,
  "tree": "scout",
  "skills": [
    {
      "id": 51708,
      "name": "Bad Guy",
      "description": "{#005060}Constantly applied after learning the skill",
      "type": "buff",
      "max_lv": 15,
      "OH": 0,
      "CD": 0.0,
      "SP": 0,
      "hits": null,
      "stance": "DaggerOneHandSword DaggerShield PistolOneHandSword PistolShield",
      "property": "None",
      "sfr": null,
      "skillsr": null,
      "captionratio": {
        "1": [
          0,
          5,
          10,
          15,
          20,
          25,
          30,
          35,
          40,
          45,
          50,
          55,
          60,
          65,
          70,
          75,
          80,
          85,
          90,
          95,
          100,
          105,
          110,
          115,
          120
        ],
        "2": [
          0,
          20,
          40,
          60,
          80,
          1,
          1,
          1,
          1,
          1,
          2,
          2,
          2,
          2,
          2,
          3,
          3,
          3,
          3,
          3,
          4,
          4,
          4,
          4,
          4
        ],
        "3": [
          0,
          1,
          2,
          3,
          4,
          5,
          6,
          7,
          8,
          9,
          10,
          11,
          12,
          13,
          14,
          15,
          16,
          17,
          18,
          19,
          20,
          21,
          22,
          23,
          24
        ]
      },
      "captiontime": null,
      "def_ignore": null,
      "effect_text": "Desperado Skill Damage + CaptionRatio %\nWhen Desperado skill is Critical, decreases by CaptionRatio2 second(s) up to CaptionRatio3 second(s)"
    },
    {
      "id": 51709,
      "name": "Equilibrium",
      "description": "{#005060}Toggle Skill",
      "type": "attack",
      "max_lv": 15,
      "OH": 1,
      "CD": 15.0,
      "SP": 160,
      "hits": 1,
      "stance": "PistolOneHandSword PistolShield",
      "property": "None",
      "sfr": [
        669,
        741,
        813,
        884,
        956,
        1027,
        1099,
        1171,
        1242,
        1314,
        1385,
        1457,
        1529,
        1600,
        1672,
        1743,
        1815,
        1887,
        1958,
        2030,
        2101,
        2173,
        2245,
        2316,
        2388
      ],
      "skillsr": null,
      "captionratio": {
        "1": [
          12,
          12,
          12,
          12,
          12,
          12,
          12,
          12,
          12,
          12,
          12,
          12,
          12,
          12,
          12,
          12,
          12,
          12,
          12,
          12,
          12,
          12,
          12,
          12,
          12
        ],
        "2": [
          10,
          10,
          10,
          10,
          10,
          10,
          10,
          10,
          10,
          10,
          10,
          10,
          10,
          10,
          10,
          10,
          10,
          10,
          10,
          10,
          10,
          10,
          10,
          10,
          10
        ]
      },
      "captiontime": null,
      "def_ignore": null,
      "effect_text": "Skill Factor per strike SkillFactor %\nNumber of targets CaptionRatio\nViolent Consumed per skill cast CaptionRatio2"
    },
    {
      "id": 51710,
      "name": "Revenged",
      "description": "Quickly move to the flank or rear of the closest enemy and launch a brute force attack.",
      "type": "attack",
      "max_lv": 10,
      "OH": 0,
      "CD": 15.0,
      "SP": 146,
      "hits": 6,
      "stance": "PistolOneHandSword PistolShield",
      "property": "None",
      "sfr": [
        947,
        1113,
        1279,
        1446,
        1612,
        1778,
        1944,
        2111,
        2277,
        2443,
        2610,
        2776,
        2942,
        3109,
        3275,
        3441,
        3607,
        3774,
        3940,
        4106
      ],
      "skillsr": null,
      "captionratio": {
        "1": [
          12,
          12,
          12,
          12,
          12,
          12,
          12,
          12,
          12,
          12,
          12,
          12,
          12,
          12,
          12,
          12,
          12,
          12,
          12,
          12
        ],
        "2": [
          10,
          10,
          10,
          10,
          10,
          10,
          10,
          10,
          10,
          10,
          10,
          10,
          10,
          10,
          10,
          10,
          10,
          10,
          10,
          10
        ]
      },
      "captiontime": null,
      "def_ignore": null,
      "effect_text": "Skill Factor SkillFactor % x 6\nNumber of targets CaptionRatio\nViolent Consumed CaptionRatio2"
    },
    {
      "id": 51711,
      "name": "Deadly Fire",
      "description": "Slash diagonally in front of you to Seal(Immobilize) enemies for 1 second and quickly draw your revolver to fire a special penetrating bullet.",
      "type": "attack",
      "max_lv": 10,
      "OH": 0,
      "CD": 25.0,
      "SP": 250,
      "hits": 6,
      "stance": "PistolOneHandSword PistolShield",
      "property": "None",
      "sfr": [
        1399,
        2042,
        2686,
        3329,
        3972,
        4615,
        5258,
        5902,
        6545,
        7188,
        7831,
        8474,
        9118,
        9761,
        10404,
        11047,
        11690,
        12334,
        12977,
        13620
      ],
      "skillsr": null,
      "captionratio": {
        "1": [
          15,
          15,
          15,
          15,
          15,
          15,
          15,
          15,
          15,
          15,
          15,
          15,
          15,
          15,
          15,
          15,
          15,
          15,
          15,
          15
        ],
        "2": [
          10,
          10,
          10,
          10,
          10,
          10,
          10,
          10,
          10,
          10,
          10,
          10,
          10,
          10,
          10,
          10,
          10,
          10,
          10,
          10
        ]
      },
      "captiontime": null,
      "def_ignore": null,
      "effect_text": "Skill Factor SkillFactor % x 6\nNumber of targets CaptionRatio\nViolent Consumed CaptionRatio2"
    },
    {
      "id": 51712,
      "name": "Russian Roulette",
      "description": "Test your luck with a game of death.",
      "type": "buff",
      "max_lv": 10,
      "OH": 0,
      "CD": 4.0,
      "SP": 124,
      "hits": null,
      "stance": "PistolOneHandSword PistolShield",
      "property": "None",
      "sfr": null,
      "skillsr": null,
      "captionratio": {
        "1": [
          0,
          2,
          4,
          6,
          8,
          10,
          12,
          14,
          16,
          18,
          20,
          22,
          24,
          26,
          28,
          30,
          32,
          34,
          36,
          38
        ]
      },
      "captiontime": null,
      "def_ignore": null,
      "effect_text": "Basic skill factor of target + CaptionRatio % when consuming Violent"
    },
    {
      "id": 51713,
      "name": "Last Man Standing",
      "description": "Pronounce the Death Sentence on up to 6 enemies. Instantly fires a 6 special Penetrating Special Bullet to each target.",
      "type": "attack",
      "max_lv": 5,
      "OH": 0,
      "CD": 35.0,
      "SP": 406,
      "hits": 1,
      "stance": "PistolOneHandSword PistolShield",
      "property": "None",
      "sfr": [
        4004,
        4873,
        5742,
        6611,
        7480,
        8349,
        9218,
        10087,
        10956,
        11825,
        12694,
        13563,
        14432,
        15301,
        16170
      ],
      "skillsr": null,
      "captionratio": {
        "1": [
          15,
          15,
          15,
          15,
          15,
          15,
          15,
          15,
          15,
          15,
          15,
          15,
          15,
          15,
          15
        ],
        "2": [
          10,
          10,
          10,
          10,
          10,
          10,
          10,
          10,
          10,
          10,
          10,
          10,
          10,
          10,
          10
        ]
      },
      "captiontime": null,
      "def_ignore": null,
      "effect_text": "Skill Factor per bullet SkillFactor %\nNumber of penetrated targets per bullet CaptionRatio\nViolent Consumed CaptionRatio2"
    }
  ],
  "attributes": [
    {
      "id": 509023,
      "name": "Equilibrium: Enhance",
      "max_lv": 100,
      "category": "enhance",
      "description": "* Increases the skill factor of [Equilibrium] by 0.5% per attribute level\n\n* +10% added increase at maximum level"
    },
    {
      "id": 509024,
      "name": "Revenged: Enhance",
      "max_lv": 100,
      "category": "enhance",
      "description": "* Increases the skill factor of [Revenged] by 0.5% per attribute level\n\n* +10% added increase at maximum level"
    },
    {
      "id": 509025,
      "name": "Deadly Fire: Enhance",
      "max_lv": 100,
      "category": "enhance",
      "description": "* Increases the skill factor of [Deadly Fire] by 0.5% per attribute level\n\n* +10% added increase at maximum level"
    },
    {
      "id": 509026,
      "name": "Russian Roulette: Enhance",
      "max_lv": 100,
      "category": "enhance",
      "description": "* Increases [Russian Roulette]'s enhance effects by 0.5% per attribute level\n\n* +10% added increase at maximum level"
    },
    {
      "id": 509027,
      "name": "Last Man Standing: Enhance",
      "max_lv": 100,
      "category": "enhance",
      "description": "* Increases the skill factor of [Last Man Standing] by 0.5% per attribute level\n\n* +10% added increase at maximum level"
    },
    {
      "id": 509028,
      "name": "[Arts] Equilibrium: Enhanced Upgrade",
      "max_lv": 30,
      "category": "arts_upgrade",
      "description": "* Increases the enhance effect of [Equilibrium] by 1.25% per attribute level"
    },
    {
      "id": 509029,
      "name": "[Arts] Revenged: Enhanced Upgrade",
      "max_lv": 30,
      "category": "arts_upgrade",
      "description": "* Increases the Skill Factor of [Revenged] by 1.25% per attribute level"
    },
    {
      "id": 509030,
      "name": "[Arts] Deadly Fire: Enhanced Upgrade",
      "max_lv": 30,
      "category": "arts_upgrade",
      "description": "* Increases the Skill Factor of [Deadly Fire] by 1.25% per attribute level"
    },
    {
      "id": 509031,
      "name": "[Arts] Russian Roulette: Enhanced Upgrade",
      "max_lv": 30,
      "category": "arts_upgrade",
      "description": "* Increases the enhance effect of [Russian Roulette] by 1.25% per attribute level"
    },
    {
      "id": 509032,
      "name": "[Arts] Last Man Standing: Enhanced Upgrade",
      "max_lv": 30,
      "category": "arts_upgrade",
      "description": "* Increases the Skill Factor of [Last Man Standing] by 1.25% per attribute level"
    },
    {
      "id": 509033,
      "name": "Bad Guy: Death Approaching",
      "max_lv": 1,
      "category": "modifier",
      "description": "* Desperado Final Damage increases by 3% when Desperado skill is accurately hit (Up to 5 stacks)\n\n* 5 stacks applied when Last Man Standing is cast"
    },
    {
      "id": 509034,
      "name": "[Arts] Russian Roulette: Death Awaiting",
      "max_lv": 1,
      "category": "arts_behavior",
      "description": "* Cooldown caused by [Russian Roulette] UNLUCKY changed 10 seconds\n\n* Increases SP consumption by 200%"
    },
    {
      "id": 509035,
      "name": "Revenged: Death Trajectory",
      "max_lv": 1,
      "category": "modifier",
      "description": "* Skill factor of the Revenged cast within 3 seconds after [Equilibrium] Retreat Shot increases by (4 x [Equilibrium] level)%\n\n* Increases SP consumption by 50%\n\n* Can only be changed in towns."
    },
    {
      "id": 509036,
      "name": "Deadly Fire: Death Gravity",
      "max_lv": 1,
      "category": "modifier",
      "description": "* Skill factor of the Deadly Fire cast within 3 seconds after [Equilibrium] charging charging increases by (5 x [Equilibrium] level)%\n\n* Increases SP consumption by 50%\n\n* Can only be changed in towns."
    },
    {
      "id": 509037,
      "name": "Russian Roulette: Death Impulse",
      "max_lv": 1,
      "category": "modifier",
      "description": "* [Russian Roulette] UNLUCKY chance doubles, but the increase rate of Violent factor doubles\n\n* Increases SP consumption by 20%\n\n* Any existing Violent buff will be removed"
    },
    {
      "id": 509038,
      "name": "[Arts] Last Man Standing: Death Sentence",
      "max_lv": 1,
      "category": "arts_behavior",
      "description": "* The target penetration attack of [Last Man Standing] is changed to non-penetrable skill but the number of hit doubles per bullet\n\n* Increases SP consumption by 50%"
    },
    {
      "id": 509039,
      "name": "Equilibrium: Maintain Distance",
      "max_lv": 1,
      "category": "modifier",
      "description": "* Charge attack disappears."
    }
  ]
}